best_shot/__init__.py
best_shot/async_client.py
best_shot/client.py
best_shot/types.py
best_shot/embed/__init__.py
best_shot/embed/base.py
best_shot/embed/litellm.py
best_shot/embed/transformers.py
best_shot/store/__init__.py
best_shot/store/base.py
best_shot/store/chroma.py
best_shot/store/memory.py
best_shot/store/milvus.py
best_shot/store/mongodb.py
best_shot/store/pg.py
best_shot/store/pinecone.py
best_shot/store/qdrant.py
best_shot/store/vespa.py
best_shot/store/weaviate.py
best_shot/utils/asyncio.py
best_shot/utils/format.py
best_shot-0.1.1.dist-info/METADATA
best_shot-0.1.1.dist-info/WHEEL
best_shot-0.1.1.dist-info/RECORD
