Metadata-Version: 2.3
Name: best-shot
Version: 0.1.1
Summary: Take your best shot
Author-email: cyrus <cyrus@zenbase.ai>, behradkhorram <behrad@zenbase.ai>
Requires-Python: >=3.8
Requires-Dist: asyncer>=0.0.8
Requires-Dist: ujson>=5.10.0
Provides-Extra: memory
Requires-Dist: numpy<2; extra == 'memory'
Provides-Extra: transformers
Requires-Dist: sentence-transformers>=3.2.1; extra == 'transformers'
Requires-Dist: transformers>=4.46.2; extra == 'transformers'
